{
    "sync_status": "PULSING_GREEN",
    "recursive_singularity": "ACTIVE_SOTA",
    "active_modules_matrix": {
        "Affiliate-Network-Siphon": {
            "status": "ACTIVE_INFINITE ✅",
            "pulse_time": "2026-07-01 20:25:13 UTC"
        },
        "Filter-BotAI": {
            "status": "ACTIVE_INFINITE ✅",
            "pulse_time": "2026-07-01 20:25:13 UTC"
        },
        "Drone-Matrix": {
            "status": "ACTIVE_INFINITE ✅",
            "pulse_time": "2026-07-01 20:25:13 UTC"
        },
        "Bing-Siphon": {
            "status": "ACTIVE_INFINITE ✅",
            "pulse_time": "2026-07-01 20:25:13 UTC"
        },
        "ADTech-Traffic": {
            "status": "ACTIVE_INFINITE ✅",
            "pulse_time": "2026-07-01 20:25:13 UTC"
        },
        "AI-Cache-Siphon": {
            "status": "ACTIVE_INFINITE ✅",
            "pulse_time": "2026-07-01 20:25:13 UTC"
        },
        "Social-Preview-Siphon": {
            "status": "ACTIVE_INFINITE ✅",
            "pulse_time": "2026-07-01 20:25:13 UTC"
        },
        "Google-Siphon": {
            "status": "ACTIVE_INFINITE ✅",
            "pulse_time": "2026-07-01 20:25:13 UTC"
        }
    },
    "timestamp": "2026-07-01 20:25:13 UTC"
}